common_packages/__init__.py
common_packages/db_utils/__init__.py
common_packages/db_utils/mysql.py
common_packages/file_storage/__init__.py
common_packages/file_storage/file_interface.py
common_packages/file_storage/local.py
common_packages/file_storage/tencent_cos.py
common_packages/geography/__init__.py
common_packages/geography/district_amap.py
common_packages/geography/search_amap.py
common_packages/llm/__init__.py
common_packages/llm/aliyun_qwen.py
common_packages/llm/azure_gpt.py
common_packages/llm/baidu_ernie.py
common_packages/oauth2/__init__.py
common_packages/oauth2/google.py
common_packages/parse_subtitle/__init__.py
common_packages/parse_subtitle/aa.vtt
common_packages/parse_subtitle/parse_srt_file.py
common_packages/pdf/__init__.py
common_packages/pdf/aaa.py
common_packages/pdf/local_parse.py
common_packages/sms/__init__.py
common_packages/sms/interface.py
common_packages/sms/tencent_sms.py
common_packages/translate/__init__.py
common_packages/translate/_youdao.py
common_packages/translate/microsoft.py
common_packages/tts/__init__.py
common_packages/tts/microsoft.py
common_packages/utils/__init__.py
common_packages/utils/image_utils.py
common_packages/utils/tencent_utils.py
common_packages/utils/utils.py
common_packages/weather/__init__.py
common_packages/weather/amap.py
common_packages/weather/wanwei.py
common_packages-0.2.10.dist-info/METADATA
common_packages-0.2.10.dist-info/WHEEL
common_packages-0.2.10.dist-info/licenses/LICENSE
common_packages-0.2.10.dist-info/RECORD
