Metadata-Version: 2.4
Name: common-packages
Version: 0.2.10
Summary: 封装了一些常用功能,GitHub: https://github.com/jiangwenfan/common_packages/tree/main
License: MIT
License-File: LICENSE
Author: evans.jiang
Author-email: evans.jiang@gmail.com
Requires-Python: >=3.11,<4.0
Classifier: License :: OSI Approved :: MIT License
Classifier: Programming Language :: Python :: 3
Classifier: Programming Language :: Python :: 3.11
Classifier: Programming Language :: Python :: 3.12
Classifier: Programming Language :: Python :: 3.13
Classifier: Programming Language :: Python :: 3.14
Requires-Dist: requests (>=2.31.0,<3.0.0)
